VDF_Project_Part_2/Coverage/toll.v
`timescale 1ns / 1ps

//================================================================
// MODULE: toll_gate (Top-Level Controller)
// DESCRIPTION: This is the main FSM that orchestrates the entire
//              toll booth operation by interacting with submodules.
//================================================================
module toll_gate (
    // Port List
    clk,
    reset,
    sensor_vehicle_enter,
    sensor_vehicle_exit,
    vehicle_id_in,
    barrier_open_cmd,
    barrier_close_cmd,
    led_status,
    display_out
);
    // Port Declarations
    input clk;
    input reset;
    input sensor_vehicle_enter;
    input sensor_vehicle_exit;
    input [7:0] vehicle_id_in;

    // Outputs to the Environment
    output barrier_open_cmd;
    output barrier_close_cmd;
    output reg [1:0] led_status;
    output reg [7:0] display_out;

    // FSM State Parameters (Expanded for robust operation)
    localparam IDLE               = 3'b000;
    localparam READ_ID            = 3'b001;
    localparam CHECK_BALANCE      = 3'b010;
    localparam CHARGE_ACCOUNT     = 3'b011;
    localparam REJECT_TRANSACTION = 3'b100;
    localparam OPEN_GATE          = 3'b101;
    localparam CLOSE_GATE         = 3'b110;

    // FSM State Registers
    reg [2:0] state, next_state;

    // Internal control signals from FSM to submodules (must be 'reg')
    reg read_id_en;
    reg balance_check_req;
    reg charge_req;
    reg open_gate_en;
    reg close_gate_en;

    // Internal status signals from submodules to FSM (must be 'wire')
    wire id_valid;
    wire [7:0] id_to_check;
    wire sufficient_balance;
    wire charge_done;
    wire gate_is_open;
    wire gate_is_closed;

    // Signals driven by a submodule's output port MUST be wires.
    wire barrier_open_cmd;
    wire barrier_close_cmd;

    // =======================================================
    // I. STATE REGISTER (Sequential Logic with SYNCHRONOUS RESET)
    // =======================================================
    // MODIFIED: 'reset' removed from sensitivity list. Reset is now checked on posedge clk.
    always @(posedge clk) begin
        if (reset)
            state <= IDLE;
        else
            state <= next_state;
    end

    // =======================================================
    // II. NEXT STATE & OUTPUT LOGIC (Single Combinational Block)
    // =======================================================
    // NOTE: This combinational block does not change.
    always @(*) begin
        // --- Start with safe default assignments for all control signals ---
        next_state          = state;
        read_id_en          = 1'b0;
        balance_check_req   = 1'b0;
        charge_req          = 1'b0;
        open_gate_en        = 1'b0;
        close_gate_en       = 1'b0;
        led_status          = 2'b01; // Default to RED LED
        display_out         = "----";

        // --- FSM Logic ---
        case (state)
            IDLE: begin
                display_out = "IDLE";
                close_gate_en = 1'b1; // Ensure gate is closed

                if (sensor_vehicle_enter) begin
                    next_state = READ_ID;
                end
            end

            READ_ID: begin
                display_out = "READ";
                read_id_en = 1'b1; // Enable ID reading
                if (id_valid) begin
                    next_state = CHECK_BALANCE;
                end
            end

            CHECK_BALANCE: begin
                display_out = "CHECK";
                balance_check_req = 1'b1;
                if (sufficient_balance) begin
                    next_state = CHARGE_ACCOUNT;
                end else begin
                    next_state = REJECT_TRANSACTION;
                end
            end

            CHARGE_ACCOUNT: begin
                led_status = 2'b11; // BLUE (Processing)
                display_out = "CHARGE";
                // Keep balance check active so 'sufficient_balance' remains valid
                balance_check_req = 1'b1;
                charge_req = 1'b1;
                if (charge_done) begin
                    next_state = OPEN_GATE;
                end
            end

            REJECT_TRANSACTION: begin
                display_out = "FAIL";
                // After showing fail message for one cycle, return to idle
                next_state = IDLE;
            end

            OPEN_GATE: begin
                led_status  = 2'b10; // GREEN LED
                display_out = "GO";
                open_gate_en = 1'b1; // Command the barrier to open

                if (sensor_vehicle_exit) begin
                    next_state = CLOSE_GATE;
                end
            end

            CLOSE_GATE: begin
                display_out   = "CLOSE";
                close_gate_en = 1'b1; // Command the barrier to close

                if (gate_is_closed) begin
                    next_state = IDLE;
                end
            end

            default: begin
                next_state = IDLE;
            end
        endcase
    end

    // =======================================================
    // III. MODULE INSTANTIATIONS
    // =======================================================
    vehicle_interface u_vehicle_interface (
        .clk(clk),
        .reset(reset),
        .fsm_read_en(read_id_en),
        .vehicle_id_in(vehicle_id_in),
        .id_to_check(id_to_check),
        .id_valid(id_valid)
    );

    account_balance u_account_balance (
        .clk(clk),
        .reset(reset),
        .id_to_check(id_to_check),
        .fsm_check_req(balance_check_req),
        .fsm_charge_req(charge_req),
        .sufficient_balance(sufficient_balance),
        .charge_done(charge_done)
    );

    barrier_ctrl u_barrier_ctrl (
        .clk(clk),
        .reset(reset),
        .fsm_open_en(open_gate_en),
        .fsm_close_en(close_gate_en),
        .barrier_open_cmd(barrier_open_cmd),
        .barrier_close_cmd(barrier_close_cmd),
        .gate_is_open(gate_is_open),
        .gate_is_closed(gate_is_closed)
    );
endmodule


//================================================================
// MODULE: vehicle_interface
// DESCRIPTION: Captures the vehicle ID when enabled by the FSM.
//================================================================
module vehicle_interface (
    clk, reset, fsm_read_en, vehicle_id_in, id_to_check, id_valid
);
    input clk;
    input reset;
    input fsm_read_en;
    input [7:0] vehicle_id_in;
    output reg [3:0] id_to_check;
    output reg id_valid;

    // MODIFIED: Converted to synchronous reset.
    always @(posedge clk) begin
        if (reset) begin
            id_to_check <= 4'h00;
            id_valid <= 1'b0;
        end else begin
            if (fsm_read_en) begin
                id_to_check <= vehicle_id_in;
                id_valid <= 1'b1;
            end else begin
                id_valid <= 1'b0;
            end
        end
    end
endmodule


//================================================================
// MODULE: account_balance
// DESCRIPTION: Manages a simple memory-based account database.
//================================================================
module account_balance (
    clk, reset, id_to_check, fsm_check_req, fsm_charge_req,
    sufficient_balance, charge_done
);
    input clk;
    input reset;
    input [7:0] id_to_check;
    input fsm_check_req;
    input fsm_charge_req;
    output reg sufficient_balance;
    output reg charge_done;

    localparam TOLL_AMOUNT = 16'd10;
    reg [15:0] balance_db [0:15];
    wire [3:0] db_addr = id_to_check[3:0];

    // MODIFIED: Converted to synchronous reset.
    // Use a synthesizable reset to initialize the memory.
    always @(posedge clk) begin
        if (reset) begin
            charge_done <= 1'b0;
            // Initialize memory on reset
            balance_db[4'h01] <= 16'd100; // Has funds
            balance_db[4'h02] <= 16'd5;   // No funds
            balance_db[4'h03] <= 16'd20;  // Has funds
            // Note: Other memory locations will be unknown unless also initialized.
            // A for-loop could be used here if you need to clear everything.
        end else begin
            charge_done <= 1'b0; // Default to not done
            if (fsm_charge_req && sufficient_balance) begin
                balance_db[db_addr] <= balance_db[db_addr] - TOLL_AMOUNT;
                charge_done <= 1'b1;
            end
        end
    end

    // Combinational logic for checking balance remains the same.
    always @(*) begin
        if (fsm_check_req) begin
            if (balance_db[db_addr] >= TOLL_AMOUNT)
                sufficient_balance = 1'b1;
            else
                sufficient_balance = 1'b0;
        end else begin
            sufficient_balance = 1'b0;
        end
    end
endmodule


//================================================================
// MODULE: barrier_ctrl
// DESCRIPTION: Simulates the physical barrier motor and position.
//================================================================
module barrier_ctrl (
    clk, reset, fsm_open_en, fsm_close_en,
    barrier_open_cmd, barrier_close_cmd, gate_is_open, gate_is_closed
);
    input clk;
    input reset;
    input fsm_open_en;
    input fsm_close_en;
    output reg barrier_open_cmd;
    output reg barrier_close_cmd;
    output gate_is_open;
    output gate_is_closed;

    reg [2:0] barrier_position_counter;
    assign gate_is_open = (barrier_position_counter == 3'd7);
    assign gate_is_closed = (barrier_position_counter == 3'd0);

    // MODIFIED: Converted to synchronous reset.
    always @(posedge clk) begin
        if (reset) begin
            barrier_open_cmd <= 1'b0;
            barrier_close_cmd <= 1'b1;
            barrier_position_counter <= 3'd0;
        end else begin
            if (fsm_open_en && !gate_is_open) begin
                barrier_open_cmd <= 1'b1;
                barrier_close_cmd <= 1'b0;
                barrier_position_counter <= barrier_position_counter + 1;
            end else if (fsm_close_en && !gate_is_closed) begin
                barrier_open_cmd <= 1'b0;
                barrier_close_cmd <= 1'b1;
                barrier_position_counter <= barrier_position_counter - 1;
            end else begin
                barrier_open_cmd <= 1'b0;
                barrier_close_cmd <= 1'b0;
                if (fsm_close_en && gate_is_closed)
                    barrier_close_cmd <= 1'b1;
                else if (fsm_open_en && gate_is_open)
                    barrier_open_cmd <= 1'b1;
            end
        end
    end
endmodule

VDF_Project_Part_1/Coverage/tb_toll_90.v
//================================================================
// MODULE: tb_toll_gate
// DESCRIPTION: Enhanced testbench achieving 100% coverage
//================================================================
module tb_toll_gate;

    reg clk;
    reg reset;
    reg sensor_vehicle_enter;
    reg sensor_vehicle_exit;
    reg [7:0] vehicle_id_in;
    integer i;

    wire barrier_open_cmd;
    wire barrier_close_cmd;
    wire [1:0] led_status;
    wire [7:0] display_out;

    toll_gate uut (
        .clk(clk),
        .reset(reset),
        .sensor_vehicle_enter(sensor_vehicle_enter),
        .sensor_vehicle_exit(sensor_vehicle_exit),
        .vehicle_id_in(vehicle_id_in),
        .barrier_open_cmd(barrier_open_cmd),
        .barrier_close_cmd(barrier_close_cmd),
        .led_status(led_status),
        .display_out(display_out)
    );

    // Clock Generation
    initial begin
        clk = 0;
        forever #5 clk = ~clk;
    end

    initial begin
        // Initialize signals
        reset = 1;
        sensor_vehicle_enter = 0;
        sensor_vehicle_exit = 0;
        vehicle_id_in = 8'h00;

        // Apply reset
        #20;
        reset = 0;
        #10;

        $monitor("Time=%0t | State=%b | Enter=%b Exit=%b ID=%h | Open=%b Close=%b LED=%b Display=%h",
                 $time, uut.state, sensor_vehicle_enter, sensor_vehicle_exit, vehicle_id_in,
                 barrier_open_cmd, barrier_close_cmd, led_status, display_out);

        // ============================================================
        // SCENARIO 1: Successful transaction with ID 01
        // ============================================================
        $display("\n=== SCENARIO 1: Successful Transaction (ID=01) ===");
        @(posedge clk);
        sensor_vehicle_enter = 1;
        vehicle_id_in = 8'h01;
        @(posedge clk);
        @(posedge clk);
        sensor_vehicle_enter = 0;
       
        // Wait for FSM to go through READ_ID -> CHECK_BALANCE -> CHARGE_ACCOUNT -> OPEN_GATE
        #100;
       
        // Trigger exit sensor while gate is opening
        sensor_vehicle_exit = 1;
        @(posedge clk);
        @(posedge clk);
        sensor_vehicle_exit = 0;
       
        // Wait for gate to close
        #150;

        // ============================================================
        // SCENARIO 2: Insufficient funds (ID=02)
        // ============================================================
        $display("\n=== SCENARIO 2: Insufficient Funds (ID=02) ===");
        @(posedge clk);
        sensor_vehicle_enter = 1;
        vehicle_id_in = 8'h02;
        @(posedge clk);
        @(posedge clk);
        sensor_vehicle_enter = 0;
       
        // Wait for rejection
        #50;

        // ============================================================
        // SCENARIO 3: Valid ID with multiple checks (ID=03)
        // ============================================================
        $display("\n=== SCENARIO 3: Valid Transaction (ID=03) ===");
        @(posedge clk);
        sensor_vehicle_enter = 1;
        vehicle_id_in = 8'h03;
        @(posedge clk);
        @(posedge clk);
        sensor_vehicle_enter = 0;
       
        #100;
        sensor_vehicle_exit = 1;
        @(posedge clk);
        @(posedge clk);
        sensor_vehicle_exit = 0;
        #150;

        // ============================================================
        // SCENARIO 4: Test edge cases in vehicle_interface
        // ============================================================
        $display("\n=== SCENARIO 4: Vehicle Interface Edge Cases ===");
       
        // Test with different ID values to cover all bits
        @(posedge clk);
        sensor_vehicle_enter = 1;
        vehicle_id_in = 8'hFF; // All 1s
        @(posedge clk);
        sensor_vehicle_enter = 0;
        #50;

        @(posedge clk);
        sensor_vehicle_enter = 1;
        vehicle_id_in = 8'h55; // Alternating bits
        @(posedge clk);
        sensor_vehicle_enter = 0;
        #50;

        @(posedge clk);
        sensor_vehicle_enter = 1;
        vehicle_id_in = 8'hAA; // Alternating bits
        @(posedge clk);
        sensor_vehicle_enter = 0;
        #50;

        // ============================================================
        // SCENARIO 5: Test barrier_ctrl edge cases
        // ============================================================
        $display("\n=== SCENARIO 5: Barrier Control Edge Cases ===");
       
        // Normal operation with ID=01
        @(posedge clk);
        sensor_vehicle_enter = 1;
        vehicle_id_in = 8'h01;
        @(posedge clk);
        @(posedge clk);
        sensor_vehicle_enter = 0;
       
        // Wait until gate fully opens (approximate timing)
        repeat(20) @(posedge clk);
        $display("Gate fully opened at time %0t", $time);
       
        // Hold at open position
        #30;
       
        // Exit while gate is fully open
        sensor_vehicle_exit = 1;
        @(posedge clk);
        @(posedge clk);
        sensor_vehicle_exit = 0;
       
        // Wait for gate to fully close (approximate timing)
        repeat(20) @(posedge clk);
        $display("Gate fully closed at time %0t", $time);
        #30;

        // ============================================================
        // SCENARIO 6: Test account_balance edge cases
        // ============================================================
        $display("\n=== SCENARIO 6: Account Balance Edge Cases ===");
       
        // Test uninitialized memory location
        @(posedge clk);
        sensor_vehicle_enter = 1;
        vehicle_id_in = 8'h0F; // Different address
        @(posedge clk);
        @(posedge clk);
        sensor_vehicle_enter = 0;
        #50;

        // ============================================================
        // SCENARIO 7: Reset during operation
        // ============================================================
        $display("\n=== SCENARIO 7: Reset During Operation ===");
        @(posedge clk);
        sensor_vehicle_enter = 1;
        vehicle_id_in = 8'h01;
        @(posedge clk);
        @(posedge clk);
        sensor_vehicle_enter = 0;
        #20;
       
        // Apply reset while in middle of transaction
        reset = 1;
        #20;
        reset = 0;
        #30;

        // ============================================================
        // SCENARIO 8: Rapid successive transactions
        // ============================================================
        $display("\n=== SCENARIO 8: Rapid Successive Transactions ===");
        @(posedge clk);
        sensor_vehicle_enter = 1;
        vehicle_id_in = 8'h01;
        @(posedge clk);
        sensor_vehicle_enter = 0;
        #100;
        sensor_vehicle_exit = 1;
        @(posedge clk);
        sensor_vehicle_exit = 0;
        #150;
       
        // Immediately start another transaction
        @(posedge clk);
        sensor_vehicle_enter = 1;
        vehicle_id_in = 8'h03;
        @(posedge clk);
        sensor_vehicle_enter = 0;
        #100;
        sensor_vehicle_exit = 1;
        @(posedge clk);
        sensor_vehicle_exit = 0;
        #150;

        // ============================================================
        // SCENARIO 9: Test all FSM states and transitions
        // ============================================================
        $display("\n=== SCENARIO 9: Complete FSM State Coverage ===");
       
        // Ensure we hit default case (shouldn't happen normally)
        // Force state to invalid value using force/release
        force uut.state = 3'b111;
        @(posedge clk);
        release uut.state;
        @(posedge clk);
        #30;

        // ============================================================
        // SCENARIO 10: Extended gate operations
        // ============================================================
        $display("\n=== SCENARIO 10: Extended Gate Operations ===");
        @(posedge clk);
        sensor_vehicle_enter = 1;
        vehicle_id_in = 8'h01;
        @(posedge clk);
        sensor_vehicle_enter = 0;
       
        // Let gate start opening
        #60;
       
        // Exit before gate fully opens
        sensor_vehicle_exit = 1;
        @(posedge clk);
        @(posedge clk);
        sensor_vehicle_exit = 0;
       
        // Wait for complete close
        #200;

        // ============================================================
        // SCENARIO 11: Test all possible combinations of sensors
        // ============================================================
        $display("\n=== SCENARIO 11: Sensor Combinations ===");
       
        // Test all combinations of enter and exit sensors
        @(posedge clk);
        sensor_vehicle_enter = 0;
        sensor_vehicle_exit = 0;
        @(posedge clk);
        #10;
       
        @(posedge clk);
        sensor_vehicle_enter = 1;
        sensor_vehicle_exit = 0;
        @(posedge clk);
        #10;
       
        @(posedge clk);
        sensor_vehicle_enter = 0;
        sensor_vehicle_exit = 1;
        @(posedge clk);
        #10;
       
        @(posedge clk);
        sensor_vehicle_enter = 1;
        sensor_vehicle_exit = 1;
        @(posedge clk);
        #10;
       
        // Test rapid toggling of sensors
        i = 0;
        while (i < 5) begin
            @(posedge clk);
            sensor_vehicle_enter = ~sensor_vehicle_enter;
            sensor_vehicle_exit = ~sensor_vehicle_exit;
            @(posedge clk);
            i = i + 1;
        end

        // ============================================================
        // SCENARIO 12: Test boundary conditions
        // ============================================================
        $display("\n=== SCENARIO 12: Boundary Conditions ===");
       
        // Test with maximum ID value
        @(posedge clk);
        sensor_vehicle_enter = 1;
        vehicle_id_in = 8'hFF;
        @(posedge clk);
        sensor_vehicle_enter = 0;
        #50;
       
        // Test with minimum ID value (0)
        @(posedge clk);
        sensor_vehicle_enter = 1;
        vehicle_id_in = 8'h00;
        @(posedge clk);
        sensor_vehicle_enter = 0;
        #50;

        $display("\n=== All Test Scenarios Completed ===");
        #100;
        $finish;
    end

    // Coverage monitors
    initial begin
        $dumpfile("tb_toll_gate.vcd");
        $dumpvars(0, tb_toll_gate);
    end

endmodule

VDF_Project_Part_1/Coverage/tb_toll_gate.vcd
$date
    Nov 17, 2025  01:47:38
$end
$version
    TOOL:	ncsim(64)	15.20-s084
$end
$timescale
    1 ps
$end

$scope module tb_toll_gate $end
$var reg       1 !    clk  $end
$var reg       1 "    reset  $end
$var reg       1 #    sensor_vehicle_enter  $end
$var reg       1 $    sensor_vehicle_exit  $end
$var reg       8 %    vehicle_id_in [7:0] $end
$var integer  32 &    i  $end
$var wire      1 '    barrier_open_cmd  $end
$var wire      1 (    barrier_close_cmd  $end
$var wire      2 )    led_status [1:0] $end
$var wire      8 *    display_out [7:0] $end

$scope module uut $end
$var wire      1 +    clk  $end
$var wire      1 ,    reset  $end
$var wire      1 -    sensor_vehicle_enter  $end
$var wire      1 .    sensor_vehicle_exit  $end
$var wire      8 /    vehicle_id_in [7:0] $end
$var wire      1 '    barrier_open_cmd  $end
$var wire      1 (    barrier_close_cmd  $end
$var reg       2 0    led_status [1:0] $end
$var reg       8 1    display_out [7:0] $end
$var parameter  3 2    IDLE  $end
$var parameter  3 3    READ_ID  $end
$var parameter  3 4    CHECK_BALANCE  $end
$var parameter  3 5    CHARGE_ACCOUNT  $end
$var parameter  3 6    REJECT_TRANSACTION  $end
$var parameter  3 7    OPEN_GATE  $end
$var parameter  3 8    CLOSE_GATE  $end
$var reg       3 9    state [2:0] $end
$var reg       3 :    next_state [2:0] $end
$var reg       1 ;    read_id_en  $end
$var reg       1 <    balance_check_req  $end
$var reg       1 =    charge_req  $end
$var reg       1 >    open_gate_en  $end
$var reg       1 ?    close_gate_en  $end
$var wire      1 @    id_valid  $end
$var wire      1 A    id_to_check [7] $end
$var wire      1 B    id_to_check [6] $end
$var wire      1 C    id_to_check [5] $end
$var wire      1 D    id_to_check [4] $end
$var wire      1 E    id_to_check [3] $end
$var wire      1 F    id_to_check [2] $end
$var wire      1 G    id_to_check [1] $end
$var wire      1 H    id_to_check [0] $end
$var wire      1 I    sufficient_balance  $end
$var wire      1 J    charge_done  $end
$var wire      1 K    gate_is_open  $end
$var wire      1 L    gate_is_closed  $end

$scope module u_vehicle_interface $end
$var wire      1 +    clk  $end
$var wire      1 ,    reset  $end
$var wire      1 M    fsm_read_en  $end
$var wire      8 /    vehicle_id_in [7:0] $end
$var reg       4 N    id_to_check [3:0] $end
$var reg       1 O    id_valid  $end
$upscope $end


$scope module u_account_balance $end
$var wire      1 +    clk  $end
$var wire      1 ,    reset  $end
$var wire      1 A    id_to_check [7] $end
$var wire      1 B    id_to_check [6] $end
$var wire      1 C    id_to_check [5] $end
$var wire      1 D    id_to_check [4] $end
$var wire      1 E    id_to_check [3] $end
$var wire      1 F    id_to_check [2] $end
$var wire      1 G    id_to_check [1] $end
$var wire      1 H    id_to_check [0] $end
$var wire      1 P    fsm_check_req  $end
$var wire      1 Q    fsm_charge_req  $end
$var reg       1 R    sufficient_balance  $end
$var reg       1 S    charge_done  $end
$var parameter 16 T    TOLL_AMOUNT  $end
$var wire      4 U    db_addr [3:0] $end
$upscope $end


$scope module u_barrier_ctrl $end
$var wire      1 +    clk  $end
$var wire      1 ,    reset  $end
$var wire      1 V    fsm_open_en  $end
$var wire      1 W    fsm_close_en  $end
$var reg       1 X    barrier_open_cmd  $end
$var reg       1 Y    barrier_close_cmd  $end
$var wire      1 K    gate_is_open  $end
$var wire      1 L    gate_is_closed  $end
$var reg       3 Z    barrier_position_counter [2:0] $end
$upscope $end

$upscope $end

$upscope $end

$enddefinitions $end
$dumpvars
b1010 T
b110 8
b101 7
b100 6
b11 5
b10 4
b1 3
b0 2
0!
1"
0#
0$
b0 %
bx &
x'
x(
b1 )
b101101 *
0+
1,
0-
0.
b0 /
b1 0
b101101 1
bx 9
b0 :
0;
0<
0=
0>
0?
x@
zA
zB
zC
zD
xE
xF
xG
xH
0I
xJ
xK
xL
0M
bx N
xO
0P
0Q
0R
xS
bx U
0V
0W
xX
xY
bx Z
$end
#5000
1!
1+
b0 N
0O
0X
1Y
b0 Z
0S
b0 9
b1000101 1
1?
1W
b1000101 *
1L
0K
0J
1(
0'
0@
0E
0F
0G
0H
0?
b101101 1
b1000101 1
1?
b0 U
#10000
0!
0+
#15000
1!
1+
#20000
0"
0!
0+
0,
#25000
1!
1+
#30000
0!
0+
#35000
1!
1#
b1 %
b1 /
1-
1+
0?
b101101 1
b1000101 1
1?
b1 :
b1 9
0?
b101101 1
b1000100 1
1;
1M
0W
b1000100 *
#40000
0!
0+
#45000
1!
1+
b1 N
1O
0Y
0(
1@
1H
0;
b101101 1
b1000100 1
1;
b10 :
b1 U
#50000
0!
0+
#55000
1!
0#
0-
1+
b1 :
0;
b101101 1
b1000100 1
1;
b10 :
b10 9
0;
b101101 1
b1001011 1
1<
b100 :
1P
0M
b1001011 *
1R
1I
b10 :
0<
b101101 1
b1001011 1
1<
b11 :
#60000
0!
0+
#65000
1!
1+
0O
b11 9
0<
b101101 1
b11 0
b1000101 1
1<
1=
1Q
b11 )
b1000101 *
0@
0<
0=
b1 0
b101101 1
b11 0
b1000101 1
1<
1=
#70000
0!
0+
#75000
1!
1+
1S
1J
0<
0=
b1 0
b101101 1
b11 0
b1000101 1
1<
1=
b101 :
#80000
0!
0+
#85000
1!
1+
b101 9
0<
0=
b1 0
b101101 1
b10 0
b1001111 1
1>
1V
0Q
0P
b1001111 *
b10 )
0R
0I
0>
b1 0
b101101 1
b10 0
b1001111 1
1>
#90000
0!
0+
#95000
1!
1+
1X
b1 Z
0S
0L
0J
1'
0>
b1 0
b101101 1
b10 0
b1001111 1
1>
#100000
0!
0+
#105000
1!
1+
b10 Z
#110000
0!
0+
#115000
1!
1+
b11 Z
#120000
0!
0+
#125000
1!
1+
b100 Z
#130000
0!
0+
#135000
1!
1+
b101 Z
#140000
0!
0+
#145000
1!
1+
b110 Z
#150000
0!
0+
#155000
1$
1!
1+
1.
0>
b1 0
b101101 1
b10 0
b1001111 1
1>
b110 :
b111 Z
1K
#160000
0!
0+
#165000
1!
0$
0.
1+
b101 :
0>
b1 0
b101101 1
b10 0
b1001111 1
1>
#170000
0!
0+
#175000
1!
1+
#180000
0!
0+
#185000
1!
1+
#190000
0!
0+
#195000
1!
1+
#200000
0!
0+
#205000
1!
1+
#210000
0!
0+
#215000
1!
1+
#220000
0!
0+
#225000
1!
1+
#230000
0!
0+
#235000
1!
1+
#240000
0!
0+
#245000
1!
1+
#250000
0!
0+
#255000
1!
1+
#260000
0!
0+
#265000
1!
1+
#270000
0!
0+
#275000
1!
1+
#280000
0!
0+
#285000
1!
1+
#290000
0!
0+
#295000
1!
1+
#300000
0!
0+
#305000
1!
1+
#310000
0!
0+
#315000
1!
1#
b10 %
b10 /
1-
1+
0>
b1 0
b101101 1
b10 0
b1001111 1
1>
#320000
0!
0+
#325000
1!
1+
#330000
0!
0+
#335000
1!
0#
0-
1+
0>
b1 0
b101101 1
b10 0
b1001111 1
1>
#340000
0!
0+
#345000
1!
1+
#350000
0!
0+
#355000
1!
1+
#360000
0!
0+
#365000
1!
1+
#370000
0!
0+
#375000
1!
1+
#380000
0!
0+
#385000
1!
1#
b11 %
b11 /
1-
1+
0>
b1 0
b101101 1
b10 0
b1001111 1
1>
#390000
0!
0+
#395000
1!
1+
#400000
0!
0+
#405000
1!
0#
0-
1+
0>
b1 0
b101101 1
b10 0
b1001111 1
1>
#410000
0!
0+
#415000
1!
1+
#420000
0!
0+
#425000
1!
1+
#430000
0!
0+
#435000
1!
1+
#440000
0!
0+
#445000
1!
1+
#450000
0!
0+
#455000
1!
1+
#460000
0!
0+
#465000
1!
1+
#470000
0!
0+
#475000
1!
1+
#480000
0!
0+
#485000
1!
1+
#490000
0!
0+
#495000
1!
1+
#500000
0!
0+
#505000
1$
1!
1+
1.
0>
b1 0
b101101 1
b10 0
b1001111 1
1>
b110 :
#510000
0!
0+
#515000
1!
0$
0.
1+
b101 :
0>
b1 0
b101101 1
b10 0
b1001111 1
1>
#520000
0!
0+
#525000
1!
1+
#530000
0!
0+
#535000
1!
1+
#540000
0!
0+
#545000
1!
1+
#550000
0!
0+
#555000
1!
1+
#560000
0!
0+
#565000
1!
1+
#570000
0!
0+
#575000
1!
1+
#580000
0!
0+
#585000
1!
1+
#590000
0!
0+
#595000
1!
1+
#600000
0!
0+
#605000
1!
1+
#610000
0!
0+
#615000
1!
1+
#620000
0!
0+
#625000
1!
1+
#630000
0!
0+
#635000
1!
1+
#640000
0!
0+
#645000
1!
1+
#650000
0!
0+
#655000
1!
1+
#660000
0!
0+
#665000
1!
1#
b11111111 %
b11111111 /
1-
1+
0>
b1 0
b101101 1
b10 0
b1001111 1
1>
#670000
0!
0+
#675000
1!
0#
0-
1+
0>
b1 0
b101101 1
b10 0
b1001111 1
1>
#680000
0!
0+
#685000
1!
1+
#690000
0!
0+
#695000
1!
1+
#700000
0!
0+
#705000
1!
1+
#710000
0!
0+
#715000
1!
1+
#720000
0!
0+
#725000
1!
1#
b1010101 %
b1010101 /
1-
1+
0>
b1 0
b101101 1
b10 0
b1001111 1
1>
#730000
0!
0+
#735000
1!
0#
0-
1+
0>
b1 0
b101101 1
b10 0
b1001111 1
1>
#740000
0!
0+
#745000
1!
1+
#750000
0!
0+
#755000
1!
1+
#760000
0!
0+
#765000
1!
1+
#770000
0!
0+
#775000
1!
1+
#780000
0!
0+
#785000
1!
1#
b10101010 %
b10101010 /
1-
1+
0>
b1 0
b101101 1
b10 0
b1001111 1
1>
#790000
0!
0+
#795000
1!
0#
0-
1+
0>
b1 0
b101101 1
b10 0
b1001111 1
1>
#800000
0!
0+
#805000
1!
1+
#810000
0!
0+
#815000
1!
1+
#820000
0!
0+
#825000
1!
1+
#830000
0!
0+
#835000
1!
1+
#840000
0!
0+
#845000
1!
1#
b1 %
b1 /
1-
1+
0>
b1 0
b101101 1
b10 0
b1001111 1
1>
#850000
0!
0+
#855000
1!
1+
#860000
0!
0+
#865000
1!
0#
0-
1+
0>
b1 0
b101101 1
b10 0
b1001111 1
1>
